{
  "_class": "shapeGroup",
  "clippingMaskMode": 0,
  "do_objectID": "CAF186EF-A315-415F-B1E6-E02EB830AA1E",
  "exportOptions": {
    "_class": "exportOptions",
    "exportFormats": [
    ],
    "includedLayerIds": [
    ],
    "layerOptions": 0,
    "shouldTrim": false
  },
  "frame": {
    "_class": "rect",
    "constrainProportions": true,
    "height": 20.3163911253748,
    "width": 20.01151544663467,
    "x": 0.9942489103441403,
    "y": 0.4639738947100027
  },
  "hasClickThrough": false,
  "hasClippingMask": false,
  "isFlippedHorizontal": false,
  "isFlippedVertical": false,
  "isLocked": false,
  "isVisible": true,
  "layerListExpandedType": 0,
  "layers": [
    {
      "class": "star",
      "id": "C10A2B75-74C5-43BB-9237-8104D43FA87A"
    }
  ],
  "name": "Star",
  "nameIsFixed": false,
  "resizingConstraint": 63,
  "resizingType": 0,
  "rotation": 0,
  "shouldBreakMaskChain": false,
  "style": {
    "sharedObjectID": "B171B65C-AB6F-4ECD-905B-49F83E4526DF"
  },
  "windingRule": 1
}