{
  "_class": "group",
  "do_objectID": "569D6C28-2468-4995-8709-A1E08C201A3B",
  "exportOptions": {
    "_class": "exportOptions",
    "exportFormats": [
    ],
    "includedLayerIds": [
    ],
    "layerOptions": 0,
    "shouldTrim": false
  },
  "frame": {
    "_class": "rect",
    "constrainProportions": false,
    "height": 80,
    "width": 878,
    "x": 0,
    "y": 320
  },
  "hasClickThrough": false,
  "isFlippedHorizontal": false,
  "isFlippedVertical": false,
  "isLocked": false,
  "isVisible": true,
  "layerListExpandedType": 2,
  "layers": [
    {
      "class": "group",
      "id": "AD1ABA9F-84D3-42E2-AF8C-A77B10841F4C"
    },
    {
      "class": "group",
      "id": "92311303-B27D-4CD6-9759-97EA73A1428C"
    },
    {
      "class": "text",
      "id": "F43B183D-E512-4592-8E05-0310B7E969C0"
    }
  ],
  "name": "1",
  "nameIsFixed": true,
  "resizingConstraint": 63,
  "resizingType": 0,
  "rotation": 0,
  "shouldBreakMaskChain": false,
  "style": {
    "_class": "style",
    "endDecorationType": 0,
    "miterLimit": 10,
    "startDecorationType": 0
  }
}