{
  "_class": "group",
  "do_objectID": "F8D240AE-5E8E-4251-9759-3E36C613E525",
  "exportOptions": {
    "_class": "exportOptions",
    "exportFormats": [
    ],
    "includedLayerIds": [
    ],
    "layerOptions": 0,
    "shouldTrim": false
  },
  "frame": {
    "_class": "rect",
    "constrainProportions": false,
    "height": 121,
    "width": 162,
    "x": 358,
    "y": 482
  },
  "hasClickThrough": false,
  "isFlippedHorizontal": false,
  "isFlippedVertical": false,
  "isLocked": false,
  "isVisible": true,
  "layerListExpandedType": 0,
  "layers": [
    {
      "class": "shapeGroup",
      "id": "AB13CC75-B27E-43D5-AF6F-1D28DE665705"
    },
    {
      "class": "bitmap",
      "id": "134E027E-2DCA-4EB9-9185-1218A5822E04"
    }
  ],
  "name": "Group 24",
  "nameIsFixed": false,
  "resizingConstraint": 63,
  "resizingType": 0,
  "rotation": 0,
  "shouldBreakMaskChain": false,
  "style": {
    "_class": "style",
    "endDecorationType": 0,
    "miterLimit": 10,
    "startDecorationType": 0
  }
}